openbrain/__init__.py
openbrain/agents/__init__.py
openbrain/agents/exceptions.py
openbrain/agents/gpt_agent.py
openbrain/cli.py
openbrain/exceptions.py
openbrain/orm/__init__.py
openbrain/orm/exceptions.py
openbrain/orm/model_agent_config.py
openbrain/orm/model_chat_message.py
openbrain/orm/model_chat_session.py
openbrain/orm/model_client.py
openbrain/orm/model_common_base.py
openbrain/tools/__init__.py
openbrain/tools/callback_handler.py
openbrain/tools/models/__init__.py
openbrain/tools/models/context_aware_tool.py
openbrain/tools/models/model_leadmo_appointment.py
openbrain/tools/models/model_leadmo_contact.py
openbrain/tools/obtool.py
openbrain/tools/protocols.py
openbrain/tools/tool_convert_to_from_utc.py
openbrain/tools/tool_do_nothing.py
openbrain/tools/tool_event_mesh_tester.py
openbrain/tools/tool_get_current_time.py
openbrain/tools/tool_input_and_context_tester.py
openbrain/tools/tool_leadmo_create_appointment.py
openbrain/tools/tool_leadmo_create_contact.py
openbrain/tools/tool_leadmo_get_contact_info_from_context.py
openbrain/tools/tool_leadmo_get_simple_calendar_appointment_slots.py
openbrain/tools/tool_leadmo_stop_conversation.py
openbrain/tools/tool_leadmo_update_contact.py
openbrain/tools/tool_lls_scrub_phone_number.py
openbrain/tools/tool_simple_calculator.py
openbrain/tools/toolbox.py
openbrain/tools/util_leadmo_tools.py
openbrain/util.py
openbrain-5.9.0.dist-info/LICENSE.md
openbrain-5.9.0.dist-info/METADATA
openbrain-5.9.0.dist-info/WHEEL
openbrain-5.9.0.dist-info/entry_points.txt
openbrain-5.9.0.dist-info/RECORD
