Metadata-Version: 2.3
Name: openbrain
Version: 5.9.0
Summary: A package to interact with generative AI and build specialized generative AI workflows.
License: AGPL-3.0-only
Author: Samuel Vange
Author-email: 7166607+svange@users.noreply.github.com
Requires-Python: >=3.10,<4.0
Classifier: License :: OSI Approved :: GNU Affero General Public License v3
Classifier: Programming Language :: Python :: 3
Classifier: Programming Language :: Python :: 3.10
Classifier: Programming Language :: Python :: 3.11
Classifier: Programming Language :: Python :: 3.12
Classifier: Programming Language :: Python :: 3.13
Provides-Extra: docs
Requires-Dist: augint-leadmo (>=1.0.0,<2.0.0)
Requires-Dist: aws-lambda-powertools (>=2.25.0,<3.0.0)
Requires-Dist: aws-xray-sdk (>=2.12.0,<3.0.0)
Requires-Dist: boto3 (>=1.28.51,<2.0.0)
Requires-Dist: itsdangerous (>=2.2.0,<3.0.0)
Requires-Dist: langchain (>=0.1.0,<0.2.0)
Requires-Dist: openai (>=0.28.0,<0.29.0)
Requires-Dist: pydantic (>=2.3.0,<3.0.0)
Requires-Dist: python-dotenv (>=1.0.0,<2.0.0)
Requires-Dist: python-ulid (>=1.1.0,<2.0.0)
Requires-Dist: pytz (>=2024.1,<2025.0)
Requires-Dist: requests (>=2.31.0,<3.0.0)
Requires-Dist: sphinx (>=7.4.7,<8.0.0) ; extra == "docs"
Requires-Dist: sphinx-click (>=6.0.0,<7.0.0) ; extra == "docs"
Requires-Dist: tiktoken (>=0.5.1,<0.6.0)
Project-URL: Homepage, https://github.com/svange/openbrain
